{"v":"5.12.2","fr":25,"ip":0,"op":250,"w":1000,"h":1000,"nm":"阅读圣经","ddd":0,"assets":[{"id":"comp_0","nm":"阅读 小羊","fr":25,"layers":[{"ddd":0,"ind":7,"ty":4,"nm":"右腿","sr":1,"ks":{"o":{"a":0,"k":100,"ix":11},"r":{"a":1,"k":[{"i":{"x":[0.667],"y":[1]},"o":{"x":[0.333],"y":[0]},"t":0,"s":[0],"e":[-15]},{"i":{"x":[0.667],"y":[1]},"o":{"x":[0.333],"y":[0]},"t":17,"s":[-15],"e":[7]},{"i":{"x":[0.667],"y":[1]},"o":{"x":[0.333],"y":[0]},"t":48,"s":[7],"e":[-15]},{"i":{"x":[0.667],"y":[1]},"o":{"x":[0.333],"y":[0]},"t":80,"s":[-15],"e":[-15]},{"t":117}],"ix":10},"p":{"a":0,"k":[1166.352,1315.241,0],"ix":2,"l":2},"a":{"a":0,"k":[1122.706,1730.068,0],"ix":1,"l":2},"s":{"a":0,"k":[330,330,100],"ix":6,"l":2}},"ao":0,"shapes":[{"ty":"gr","it":[{"ty":"gr","it":[{"ind":0,"ty":"sh","ix":1,"ks":{"a":0,"k":{"i":[[-1.012,-1.688],[-0.522,0.028],[-1.29,2.108],[-0.009,0.018],[-0.075,0.16],[-0.022,0.073],[-0.03,0.064],[-0.065,0.165],[-0.006,0.025],[1.517,2.027],[0.342,0.407],[1.315,-2.794]],"o":[[0.53,0.009],[2.528,-0.123],[0.009,-0.018],[0.086,-0.155],[0.032,-0.069],[0.042,-0.064],[0.075,-0.16],[0.009,-0.018],[0.802,-2.337],[-0.316,-0.423],[-1.943,0.303],[-1.317,2.799]],"v":[[-4.182,6.183],[-2.6,6.157],[3.928,3.352],[3.959,3.299],[4.2,2.826],[4.28,2.618],[4.39,2.424],[4.601,1.936],[4.624,1.875],[2.624,-4.943],[1.632,-6.186],[-3.793,-1.187]],"c":true},"ix":2},"nm":"路径 1","mn":"ADBE Vector Shape - Group","hd":false},{"ty":"fl","c":{"a":0,"k":[0.764705896378,0.560784339905,0.427450984716,1],"ix":4},"o":{"a":0,"k":100,"ix":5},"r":1,"bm":0,"nm":"填充 1","mn":"ADBE Vector Graphic - Fill","hd":false},{"ty":"tr","p":{"a":0,"k":[0,0],"ix":2},"a":{"a":0,"k":[0,0],"ix":1},"s":{"a":0,"k":[100,100],"ix":3},"r":{"a":0,"k":0,"ix":6},"o":{"a":0,"k":100,"ix":7},"sk":{"a":0,"k":0,"ix":4},"sa":{"a":0,"k":0,"ix":5},"nm":"变换"}],"nm":"组 1","np":2,"cix":2,"bm":0,"ix":1,"mn":"ADBE Vector Group","hd":false},{"ty":"tr","p":{"a":0,"k":[1153.066,1744.602],"ix":2},"a":{"a":0,"k":[0,0],"ix":1},"s":{"a":0,"k":[100,100],"ix":3},"r":{"a":0,"k":0,"ix":6},"o":{"a":0,"k":100,"ix":7},"sk":{"a":0,"k":0,"ix":4},"sa":{"a":0,"k":0,"ix":5},"nm":"变换"}],"nm":"组 1","np":1,"cix":2,"bm":0,"ix":1,"mn":"ADBE Vector Group","hd":false},{"ty":"gr","it":[{"ind":0,"ty":"sh","ix":1,"ks":{"a":0,"k":{"i":[[-2.02,4.292],[0,0],[8.048,6.142],[0,0],[2.385,-1.602],[0,0],[1.496,-3.261],[0,0],[-0.633,-3.576],[0,0],[-1.984,-0.489],[0,0]],"o":[[0,0],[2.02,-4.292],[0,0],[-2.366,-1.631],[0,0],[-2.978,2],[0,0],[-1.514,3.301],[0,0],[0.356,2.012],[0,0],[6.057,1.185]],"v":[[18.541,10.53],[18.541,10.53],[8.131,-5.486],[-2.688,-12.943],[-10.562,-12.99],[-10.562,-12.99],[-17.403,-4.944],[-17.403,-4.944],[-18.757,5.617],[-18.757,5.617],[-14.909,9.73],[0.167,13.449]],"c":true},"ix":2},"nm":"路径 1","mn":"ADBE Vector Shape - Group","hd":false},{"ty":"fl","c":{"a":0,"k":[1,0.952941179276,0.905882358551,1],"ix":4},"o":{"a":0,"k":100,"ix":5},"r":1,"bm":0,"nm":"填充 1","mn":"ADBE Vector Graphic - Fill","hd":false},{"ty":"tr","p":{"a":0,"k":[1138.799,1736.741],"ix":2},"a":{"a":0,"k":[0,0],"ix":1},"s":{"a":0,"k":[100,100],"ix":3},"r":{"a":0,"k":0,"ix":6},"o":{"a":0,"k":100,"ix":7},"sk":{"a":0,"k":0,"ix":4},"sa":{"a":0,"k":0,"ix":5},"nm":"变换"}],"nm":"组 2","np":2,"cix":2,"bm":0,"ix":2,"mn":"ADBE Vector Group","hd":false}],"ip":0,"op":288,"st":0,"ct":1,"bm":0},{"ddd":0,"ind":8,"ty":4,"nm":"左腿","sr":1,"ks":{"o":{"a":0,"k":100,"ix":11},"r":{"a":1,"k":[{"i":{"x":[0.667],"y":[1]},"o":{"x":[0.333],"y":[0]},"t":0,"s":[0],"e":[7]},{"i":{"x":[0.667],"y":[1]},"o":{"x":[0.333],"y":[0]},"t":16,"s":[7],"e":[-15]},{"i":{"x":[0.667],"y":[1]},"o":{"x":[0.333],"y":[0]},"t":48,"s":[-15],"e":[7]},{"i":{"x":[0.667],"y":[1]},"o":{"x":[0.333],"y":[0]},"t":80,"s":[7],"e":[-15]},{"t":117}],"ix":10},"p":{"a":0,"k":[920.352,1327.741,0],"ix":2,"l":2},"a":{"a":0,"k":[1122.557,1730.239,0],"ix":1,"l":2},"s":{"a":0,"k":[330,330,100],"ix":6,"l":2}},"ao":0,"shapes":[{"ty":"gr","it":[{"ty":"gr","it":[{"ind":0,"ty":"sh","ix":1,"ks":{"a":0,"k":{"i":[[-1.012,-1.688],[-0.522,0.028],[-1.29,2.108],[-0.009,0.018],[-0.075,0.16],[-0.022,0.073],[-0.03,0.064],[-0.065,0.165],[-0.006,0.025],[1.517,2.027],[0.342,0.407],[1.315,-2.794]],"o":[[0.53,0.009],[2.528,-0.123],[0.009,-0.018],[0.086,-0.155],[0.032,-0.069],[0.042,-0.064],[0.075,-0.16],[0.009,-0.018],[0.802,-2.337],[-0.316,-0.423],[-1.943,0.303],[-1.317,2.799]],"v":[[-4.182,6.183],[-2.6,6.157],[3.928,3.352],[3.959,3.299],[4.2,2.826],[4.28,2.618],[4.39,2.424],[4.601,1.936],[4.624,1.875],[2.624,-4.943],[1.632,-6.186],[-3.793,-1.187]],"c":true},"ix":2},"nm":"路径 1","mn":"ADBE Vector Shape - Group","hd":false},{"ty":"fl","c":{"a":0,"k":[0.764705896378,0.560784339905,0.427450984716,1],"ix":4},"o":{"a":0,"k":100,"ix":5},"r":1,"bm":0,"nm":"填充 1","mn":"ADBE Vector Graphic - Fill","hd":false},{"ty":"tr","p":{"a":0,"k":[0,0],"ix":2},"a":{"a":0,"k":[0,0],"ix":1},"s":{"a":0,"k":[100,100],"ix":3},"r":{"a":0,"k":0,"ix":6},"o":{"a":0,"k":100,"ix":7},"sk":{"a":0,"k":0,"ix":4},"sa":{"a":0,"k":0,"ix":5},"nm":"变换"}],"nm":"组 1","np":2,"cix":2,"bm":0,"ix":1,"mn":"ADBE Vector Group","hd":false},{"ty":"tr","p":{"a":0,"k":[1153.066,1744.602],"ix":2},"a":{"a":0,"k":[0,0],"ix":1},"s":{"a":0,"k":[100,100],"ix":3},"r":{"a":0,"k":0,"ix":6},"o":{"a":0,"k":100,"ix":7},"sk":{"a":0,"k":0,"ix":4},"sa":{"a":0,"k":0,"ix":5},"nm":"变换"}],"nm":"组 1","np":1,"cix":2,"bm":0,"ix":1,"mn":"ADBE Vector Group","hd":false},{"ty":"gr","it":[{"ind":0,"ty":"sh","ix":1,"ks":{"a":0,"k":{"i":[[-2.02,4.292],[0,0],[8.048,6.142],[0,0],[2.385,-1.602],[0,0],[1.496,-3.261],[0,0],[-0.633,-3.576],[0,0],[-1.984,-0.489],[0,0]],"o":[[0,0],[2.02,-4.292],[0,0],[-2.366,-1.631],[0,0],[-2.978,2],[0,0],[-1.514,3.301],[0,0],[0.356,2.012],[0,0],[6.057,1.185]],"v":[[18.541,10.53],[18.541,10.53],[8.131,-5.486],[-2.688,-12.943],[-10.562,-12.99],[-10.562,-12.99],[-17.403,-4.944],[-17.403,-4.944],[-18.757,5.617],[-18.757,5.617],[-14.909,9.73],[0.167,13.449]],"c":true},"ix":2},"nm":"路径 1","mn":"ADBE Vector Shape - Group","hd":false},{"ty":"fl","c":{"a":0,"k":[1,0.952941179276,0.905882358551,1],"ix":4},"o":{"a":0,"k":100,"ix":5},"r":1,"bm":0,"nm":"填充 1","mn":"ADBE Vector Graphic - Fill","hd":false},{"ty":"tr","p":{"a":0,"k":[1138.799,1736.741],"ix":2},"a":{"a":0,"k":[0,0],"ix":1},"s":{"a":0,"k":[100,100],"ix":3},"r":{"a":0,"k":0,"ix":6},"o":{"a":0,"k":100,"ix":7},"sk":{"a":0,"k":0,"ix":4},"sa":{"a":0,"k":0,"ix":5},"nm":"变换"}],"nm":"组 2","np":2,"cix":2,"bm":0,"ix":2,"mn":"ADBE Vector Group","hd":false}],"ip":0,"op":288,"st":0,"ct":1,"bm":0}]}],"layers":[{"ddd":0,"ind":1,"ty":0,"nm":"阅读 小羊","refId":"comp_0","sr":1,"ks":{"o":{"a":0,"k":100,"ix":11},"r":{"a":0,"k":0,"ix":10},"p":{"a":0,"k":[482.5,510,0],"ix":2,"l":2},"a":{"a":0,"k":[1000,1000,0],"ix":1,"l":2},"s":{"a":0,"k":[70,70,100],"ix":6,"l":2}},"ao":0,"w":2000,"h":2000,"ip":0,"op":250,"st":0,"bm":0}],"markers":[],"props":{}}